video_diet/__init__.py
video_diet/__main__.py
video_diet/main.py
video_diet/patch_ffprobe.py
video_diet/utils.py
video_diet-0.1.10.dist-info/entry_points.txt
video_diet-0.1.10.dist-info/LICENSE
video_diet-0.1.10.dist-info/WHEEL
video_diet-0.1.10.dist-info/METADATA
video_diet-0.1.10.dist-info/RECORD
