Metadata-Version: 2.1
Name: video-diet
Version: 0.1.10
Summary: 
Home-page: https://github.com/hiancdtrsnm/video-diet
License: LGPL-3.0
Author: hian
Author-email: hiancdtrsnm@gmail.com
Requires-Python: >=3.6,<4
Classifier: License :: OSI Approved :: GNU Lesser General Public License v3 (LGPLv3)
Classifier: Programming Language :: Python :: 3
Classifier: Programming Language :: Python :: 3.6
Classifier: Programming Language :: Python :: 3.7
Classifier: Programming Language :: Python :: 3.8
Requires-Dist: ansicon (>=1.89.0,<2.0.0); sys_platform == "win32" or platform_system == "Windows"
Requires-Dist: enlighten (>=1.6.2,<2.0.0)
Requires-Dist: ffmpeg-python (>=0.2.0,<0.3.0)
Requires-Dist: ffprobe-python (>=1.0.3,<2.0.0)
Requires-Dist: filetype (>=1.0.7,<2.0.0)
Requires-Dist: pexpect (>=4.8.0,<5.0.0); sys_platform == "linux" or platform_system == "Linux"
Requires-Dist: typer[all] (>=0.3.2,<0.4.0)
Requires-Dist: wexpect (>=4.0.0,<5.0.0); sys_platform == "win32" or platform_system == "Windows"
Project-URL: Repository, https://github.com/hiancdtrsnm/video-diet
